caliban/__init__.py
caliban/__main__.py
caliban/_version.py
caliban/cli.py
caliban/expansion.py
caliban/main.py
caliban/config/__init__.py
caliban/config/experiment.py
caliban/docker/__init__.py
caliban/docker/build.py
caliban/docker/push.py
caliban/history/__init__.py
caliban/history/cli.py
caliban/history/submit.py
caliban/history/types.py
caliban/history/util.py
caliban/platform/__init__.py
caliban/platform/notebook.py
caliban/platform/run.py
caliban/platform/shell.py
caliban/platform/cloud/__init__.py
caliban/platform/cloud/core.py
caliban/platform/cloud/types.py
caliban/platform/cloud/util.py
caliban/platform/gke/__init__.py
caliban/platform/gke/cli.py
caliban/platform/gke/cluster.py
caliban/platform/gke/constants.py
caliban/platform/gke/types.py
caliban/platform/gke/util.py
caliban/resources/__init__.py
caliban/resources/caliban_launcher.py
caliban/resources/cloud_sql_proxy.py
caliban/util/__init__.py
caliban/util/argparse.py
caliban/util/auth.py
caliban/util/fs.py
caliban/util/metrics.py
caliban/util/schema.py
caliban/util/tqdm.py
tests/caliban/__init__.py
tests/caliban/test_cli.py
tests/caliban/config/__init__.py
tests/caliban/config/test_config.py
tests/caliban/config/test_experiment.py
tests/caliban/docker/__init__.py
tests/caliban/docker/test_build.py
tests/caliban/docker/test_push.py
tests/caliban/history/__init__.py
tests/caliban/history/test_history.py
tests/caliban/platform/__init__.py
tests/caliban/platform/cloud/__init__.py
tests/caliban/platform/cloud/test_types.py
tests/caliban/platform/cloud/test_util.py
tests/caliban/platform/gke/__init__.py
tests/caliban/platform/gke/test_types.py
tests/caliban/platform/gke/test_util.py
tests/caliban/resources/__init__.py
tests/caliban/resources/test_caliban_launcher.py
tests/caliban/util/__init__.py
tests/caliban/util/test_argparse.py
tests/caliban/util/test_auth.py
tests/caliban/util/test_fs.py
tests/caliban/util/test_metrics.py
tests/caliban/util/test_schema.py
tests/caliban/util/test_tqdm.py
caliban-0.4.2.dist-info/LICENSE
caliban-0.4.2.dist-info/LICENSE_SHORT
caliban-0.4.2.dist-info/METADATA
caliban-0.4.2.dist-info/WHEEL
caliban-0.4.2.dist-info/entry_points.txt
caliban-0.4.2.dist-info/top_level.txt
caliban-0.4.2.dist-info/RECORD
