Metadata-Version: 2.1
Name: caliban
Version: 0.4.2
Summary: Docker-based job runner for AI research.
Home-page: https://github.com/google/caliban
Author: Caliban Team
Author-email: samritchie@google.com
License: Apache-2.0
Requires-Python: >=3.6.0
License-File: LICENSE
License-File: LICENSE_SHORT
Requires-Dist: absl-py
Requires-Dist: blessings
Requires-Dist: commentjson
Requires-Dist: google-api-python-client
Requires-Dist: pyyaml
Requires-Dist: tqdm (>=4.45.0)
Requires-Dist: kubernetes (>=10.0.1)
Requires-Dist: google-auth (>=1.19.0)
Requires-Dist: google-cloud-core (>=1.0.3)
Requires-Dist: google-cloud-container (>=0.3.0)
Requires-Dist: psycopg2-binary (==2.9.6)
Requires-Dist: schema (==0.7.2)
Requires-Dist: urllib3 (>=1.25.7)
Requires-Dist: yaspin (>=0.16.0)
Requires-Dist: SQLAlchemy (==1.3.11)
Requires-Dist: pg8000 (==1.16.1)
